python_code_quality_analyzer/__init__.py
python_code_quality_analyzer/__main__.py
python_code_quality_analyzer-3.0.8.dist-info/METADATA
python_code_quality_analyzer-3.0.8.dist-info/WHEEL
python_code_quality_analyzer-3.0.8.dist-info/entry_points.txt
python_code_quality_analyzer-3.0.8.dist-info/licenses/LICENSE
python_code_quality_analyzer-3.0.8.dist-info/RECORD
