Metadata-Version: 2.4
Name: python-code-quality-analyzer
Version: 3.0.8
Summary: A powerful tool for analyzing Python code complexity, quality, and maintainability
Project-URL: Homepage, https://github.com/kareemaly/python-code-quality-analyzer
Project-URL: Documentation, https://github.com/kareemaly/python-code-quality-analyzer#readme
Project-URL: Repository, https://github.com/kareemaly/python-code-quality-analyzer
Project-URL: Bug Tracker, https://github.com/kareemaly/python-code-quality-analyzer/issues
Author-email: Kareem Elbahrawy <kareemelbahrawy@gmail.com>
License: MIT
License-File: LICENSE
Keywords: code analysis,complexity,maintainability,metrics,quality,static analysis
Classifier: Development Status :: 3 - Alpha
Classifier: Intended Audience :: Developers
Classifier: License :: OSI Approved :: MIT License
Classifier: Programming Language :: Python :: 3
Classifier: Programming Language :: Python :: 3.8
Classifier: Programming Language :: Python :: 3.9
Classifier: Programming Language :: Python :: 3.10
Classifier: Programming Language :: Python :: 3.11
Classifier: Programming Language :: Python :: 3.12
Classifier: Topic :: Software Development :: Libraries :: Python Modules
Classifier: Topic :: Software Development :: Quality Assurance
Classifier: Topic :: Software Development :: Testing
Requires-Python: >=3.8
Requires-Dist: click>=8.1.7
Requires-Dist: pathlib>=1.0.1
Requires-Dist: pyyaml>=6.0.1
Requires-Dist: radon>=6.0.1
Requires-Dist: rich>=13.7.0
Requires-Dist: typing-extensions>=4.9.0
